mycrawlers/mycrawlers.py
mycrawlers-0.0.2.dist-info/LICENSE
mycrawlers-0.0.2.dist-info/METADATA
mycrawlers-0.0.2.dist-info/WHEEL
mycrawlers-0.0.2.dist-info/top_level.txt
mycrawlers-0.0.2.dist-info/RECORD
